dj_cloud_error/__init__.py
dj_cloud_error/handler.py
dj_cloud_error/utils.py
dj_cloud_error-0.1.0.dist-info/AUTHORS.rst
dj_cloud_error-0.1.0.dist-info/LICENSE
dj_cloud_error-0.1.0.dist-info/METADATA
dj_cloud_error-0.1.0.dist-info/WHEEL
dj_cloud_error-0.1.0.dist-info/top_level.txt
dj_cloud_error-0.1.0.dist-info/RECORD
