Metadata-Version: 2.1
Name: dj-cloud-error
Version: 0.1.0
Summary: Report exceptions from Django to Google Stackdriver Error Reporting
Home-page: https://github.com/prismaticd/dj-cloud-error
Author: Prismatic Digital
Author-email: contact@prismaticdigital.com
License: "MIT license"
Download-URL: https://github.com/dj-stripe/dj-stripe/tarball/master
Keywords: django,google cloud,error reporting
Platform: UNKNOWN
Classifier: Development Status :: 2 - Pre-Alpha
Classifier: Intended Audience :: Developers
Classifier: License :: OSI Approved :: MIT License
Classifier: Natural Language :: English
Classifier: Programming Language :: Python :: 3
Classifier: Programming Language :: Python :: 3.6
Classifier: Programming Language :: Python :: 3.7
Classifier: Framework :: Django
Classifier: Framework :: Django :: 2.2
Requires-Python: >=3.6
Requires-Dist: Django (>=2.2)
Requires-Dist: google-cloud-error-reporting
Provides-Extra: ip
Requires-Dist: django-ipware ; extra == 'ip'
